isro.py
ISRO-0.0.1.dist-info/LICENSE
ISRO-0.0.1.dist-info/METADATA
ISRO-0.0.1.dist-info/WHEEL
ISRO-0.0.1.dist-info/top_level.txt
ISRO-0.0.1.dist-info/RECORD
