Metadata-Version: 2.1
Name: ISRO
Version: 0.0.1
Summary: Indian Space Research Organisation
Home-page: UNKNOWN
Author: Fayas Noushad
License: MIT
Project-URL: Tracker, https://github.com/FayasNoushad/ISRO/issues
Project-URL: Source, https://github.com/FayasNoushad/ISRO
Platform: UNKNOWN
Classifier: Intended Audience :: Developers
Classifier: Natural Language :: English
Classifier: Programming Language :: Python
Classifier: License :: OSI Approved :: MIT License
Classifier: Operating System :: OS Independent
Requires-Python: >=3.6
License-File: LICENSE
Requires-Dist: requests
